task_list_dev/__init__.py
task_list_dev/__main__.py
task_list_dev/tools.py
task_list_dev/utils/__init__.py
task_list_dev/utils/version.py
task_list_dev-1.0.5.dist-info/DESCRIPTION.rst
task_list_dev-1.0.5.dist-info/METADATA
task_list_dev-1.0.5.dist-info/RECORD
task_list_dev-1.0.5.dist-info/WHEEL
task_list_dev-1.0.5.dist-info/metadata.json
task_list_dev-1.0.5.dist-info/top_level.txt
tests/__init__.py
tests/test_task_list_dev.py
